picsellia_yolov5/__init__.py
picsellia_yolov5/picsellia_utils.py
picsellia_yolov5/yolov5/.dockerignore
picsellia_yolov5/yolov5/.git
picsellia_yolov5/yolov5/.gitattributes
picsellia_yolov5/yolov5/.github/ISSUE_TEMPLATE/bug-report.yml
picsellia_yolov5/yolov5/.github/ISSUE_TEMPLATE/config.yml
picsellia_yolov5/yolov5/.github/ISSUE_TEMPLATE/feature-request.yml
picsellia_yolov5/yolov5/.github/ISSUE_TEMPLATE/question.yml
picsellia_yolov5/yolov5/.github/PULL_REQUEST_TEMPLATE.md
picsellia_yolov5/yolov5/.github/dependabot.yml
picsellia_yolov5/yolov5/.github/workflows/ci-testing.yml
picsellia_yolov5/yolov5/.github/workflows/codeql-analysis.yml
picsellia_yolov5/yolov5/.github/workflows/docker.yml
picsellia_yolov5/yolov5/.github/workflows/greetings.yml
picsellia_yolov5/yolov5/.github/workflows/stale.yml
picsellia_yolov5/yolov5/.github/workflows/translate-readme.yml
picsellia_yolov5/yolov5/.gitignore
picsellia_yolov5/yolov5/.idea/.gitignore
picsellia_yolov5/yolov5/.idea/inspectionProfiles/Project_Default.xml
picsellia_yolov5/yolov5/.idea/inspectionProfiles/profiles_settings.xml
picsellia_yolov5/yolov5/.idea/modules.xml
picsellia_yolov5/yolov5/.idea/vcs.xml
picsellia_yolov5/yolov5/.idea/workspace.xml
picsellia_yolov5/yolov5/.idea/yolov5.iml
picsellia_yolov5/yolov5/.pre-commit-config.yaml
picsellia_yolov5/yolov5/CITATION.cff
picsellia_yolov5/yolov5/CONTRIBUTING.md
picsellia_yolov5/yolov5/LICENSE
picsellia_yolov5/yolov5/README.md
picsellia_yolov5/yolov5/README.zh-CN.md
picsellia_yolov5/yolov5/benchmarks.py
picsellia_yolov5/yolov5/classify/predict.py
picsellia_yolov5/yolov5/classify/train.py
picsellia_yolov5/yolov5/classify/tutorial.ipynb
picsellia_yolov5/yolov5/classify/val.py
picsellia_yolov5/yolov5/data/Argoverse.yaml
picsellia_yolov5/yolov5/data/GlobalWheat2020.yaml
picsellia_yolov5/yolov5/data/ImageNet.yaml
picsellia_yolov5/yolov5/data/Objects365.yaml
picsellia_yolov5/yolov5/data/SKU-110K.yaml
picsellia_yolov5/yolov5/data/VOC.yaml
picsellia_yolov5/yolov5/data/VisDrone.yaml
picsellia_yolov5-0.2.8.dist-info/WHEEL
picsellia_yolov5-0.2.8.dist-info/METADATA
picsellia_yolov5-0.2.8.dist-info/RECORD
