Metadata-Version: 2.1
Name: picsellia-yolov5
Version: 0.2.8
Summary: 'Picsellia wrapper for pytorch implementation of Yolov5'
Author: PN-picsell
Author-email: pierre-nicolas@picsellia.com
Requires-Python: >=3.8,<=3.10
Classifier: Programming Language :: Python :: 3
Classifier: Programming Language :: Python :: 3.8
Classifier: Programming Language :: Python :: 3.9
Classifier: Programming Language :: Python :: 3.10
Requires-Dist: Pillow (>=9.2.0,<10.0.0)
Requires-Dist: PyYAML (>=5.3.1,<6.0.0)
Requires-Dist: gitpython (>=3.1.30,<4.0.0)
Requires-Dist: ipython (>=8.10.0,<9.0.0)
Requires-Dist: matplotlib (>=3.2.2,<4.0.0)
Requires-Dist: numpy (>=1.23.5,<2.0.0)
Requires-Dist: opencv-python (>=4.1.1,<5.0.0)
Requires-Dist: pandas (>=1.1.4,<2.0.0)
Requires-Dist: psutil (>=5.9.4,<6.0.0)
Requires-Dist: pycocotools (>=2.0.6,<3.0.0)
Requires-Dist: scipy (>=1.10.0,<2.0.0)
Requires-Dist: seaborn (>=0.11.0,<0.12.0)
Requires-Dist: tensorboard (>=2.12.0,<3.0.0)
Requires-Dist: thop (>=0.1.1,<0.2.0)
Requires-Dist: torch (>=1.8.0,<2.0.0)
Requires-Dist: torchvision (>=0.9.0,<0.10.0)
Requires-Dist: tqdm (>=4.64.0,<5.0.0)
